{
  "__inputs": [
    {
      "name": "DS_PROMETHEUS",
      "label": "Prometheus",
      "description": "",
      "type": "datasource",
      "pluginId": "prometheus",
      "pluginName": "Prometheus"
    }
  ],
  "annotations": {
    "list": [
      {
        "builtIn": 1,
        "datasource": { "type": "grafana", "uid": "-- Grafana --" },
        "enable": true,
        "hide": true,
        "iconColor": "rgba(0, 211, 255, 1)",
        "name": "Annotations & Alerts",
        "target": { "limit": 100, "matchAny": false, "tags": [], "type": "dashboard" },
        "type": "dashboard"
      }
    ]
  },
  "editable": true,
  "fiscalYearStartMonth": 0,
  "graphTooltip": 1,
  "links": [],
  "panels": [
    {
      "datasource": { "type": "prometheus", "uid": "${DS_PROMETHEUS}" },
      "description": "Must stay 0 while resolute runs in shadow mode. Any non-zero value means a write executed and needs immediate investigation. Counters reset on pod restart.",
      "fieldConfig": {
        "defaults": {
          "color": { "mode": "thresholds" },
          "mappings": [],
          "noValue": "0",
          "thresholds": {
            "mode": "absolute",
            "steps": [
              { "color": "green", "value": null },
              { "color": "red", "value": 1 }
            ]
          },
          "unit": "short"
        },
        "overrides": []
      },
      "gridPos": { "h": 6, "w": 6, "x": 0, "y": 0 },
      "id": 1,
      "options": {
        "colorMode": "background",
        "graphMode": "none",
        "justifyMode": "auto",
        "orientation": "auto",
        "reduceOptions": { "calcs": ["lastNotNull"], "fields": "", "values": false },
        "textMode": "auto"
      },
      "pluginVersion": "12.0.0",
      "targets": [
        {
          "datasource": { "type": "prometheus", "uid": "${DS_PROMETHEUS}" },
          "expr": "sum(resolute_executions_total) or vector(0)",
          "legendFormat": "executions",
          "refId": "A"
        }
      ],
      "title": "Executions (shadow mode: must be 0)",
      "type": "stat"
    },
    {
      "datasource": { "type": "prometheus", "uid": "${DS_PROMETHEUS}" },
      "description": "Execution failures. Should also be 0 in shadow mode.",
      "fieldConfig": {
        "defaults": {
          "color": { "mode": "thresholds" },
          "mappings": [],
          "noValue": "0",
          "thresholds": {
            "mode": "absolute",
            "steps": [
              { "color": "green", "value": null },
              { "color": "red", "value": 1 }
            ]
          },
          "unit": "short"
        },
        "overrides": []
      },
      "gridPos": { "h": 6, "w": 6, "x": 6, "y": 0 },
      "id": 2,
      "options": {
        "colorMode": "background",
        "graphMode": "none",
        "justifyMode": "auto",
        "orientation": "auto",
        "reduceOptions": { "calcs": ["lastNotNull"], "fields": "", "values": false },
        "textMode": "auto"
      },
      "pluginVersion": "12.0.0",
      "targets": [
        {
          "datasource": { "type": "prometheus", "uid": "${DS_PROMETHEUS}" },
          "expr": "sum(resolute_execution_failures_total) or vector(0)",
          "legendFormat": "failures",
          "refId": "A"
        }
      ],
      "title": "Execution failures",
      "type": "stat"
    },
    {
      "datasource": { "type": "prometheus", "uid": "${DS_PROMETHEUS}" },
      "description": "Decision mix over the dashboard time range. The core shadow-mode signal: how often the engine picks 2160p, 1080p, or lands in the ambiguous band.",
      "fieldConfig": {
        "defaults": {
          "color": { "mode": "palette-classic" },
          "custom": { "hideFrom": { "legend": false, "tooltip": false, "viz": false } },
          "mappings": [],
          "unit": "short"
        },
        "overrides": []
      },
      "gridPos": { "h": 6, "w": 12, "x": 12, "y": 0 },
      "id": 3,
      "options": {
        "displayLabels": ["name", "value"],
        "legend": { "displayMode": "list", "placement": "right", "showLegend": true },
        "pieType": "pie",
        "reduceOptions": { "calcs": ["lastNotNull"], "fields": "", "values": false },
        "tooltip": { "mode": "single", "sort": "none" }
      },
      "pluginVersion": "12.0.0",
      "targets": [
        {
          "datasource": { "type": "prometheus", "uid": "${DS_PROMETHEUS}" },
          "expr": "sum by (resolution) (increase(resolute_decisions_total[$__range]))",
          "legendFormat": "{{ resolution }}",
          "refId": "A"
        }
      ],
      "title": "Decision mix",
      "type": "piechart"
    },
    {
      "datasource": { "type": "prometheus", "uid": "${DS_PROMETHEUS}" },
      "description": "Decisions per hour by resolution. Counters are in-memory and reset on pod restart; rate() handles the resets.",
      "fieldConfig": {
        "defaults": {
          "color": { "mode": "palette-classic" },
          "custom": {
            "drawStyle": "line",
            "fillOpacity": 15,
            "lineWidth": 2,
            "showPoints": "never",
            "spanNulls": false,
            "stacking": { "group": "A", "mode": "normal" }
          },
          "mappings": [],
          "unit": "short"
        },
        "overrides": []
      },
      "gridPos": { "h": 8, "w": 12, "x": 0, "y": 6 },
      "id": 4,
      "options": {
        "legend": { "calcs": [], "displayMode": "list", "placement": "bottom", "showLegend": true },
        "tooltip": { "mode": "multi", "sort": "desc" }
      },
      "pluginVersion": "12.0.0",
      "targets": [
        {
          "datasource": { "type": "prometheus", "uid": "${DS_PROMETHEUS}" },
          "expr": "sum by (resolution) (rate(resolute_decisions_total[$__rate_interval])) * 3600",
          "legendFormat": "{{ resolution }}",
          "refId": "A"
        }
      ],
      "title": "Decision rate (per hour)",
      "type": "timeseries"
    },
    {
      "datasource": { "type": "prometheus", "uid": "${DS_PROMETHEUS}" },
      "description": "Webhook outcomes per hour. Unauthorized, invalid, and skipped should stay near 0; sustained non-zero values point at Seerr webhook config or auth drift.",
      "fieldConfig": {
        "defaults": {
          "color": { "mode": "palette-classic" },
          "custom": {
            "drawStyle": "line",
            "fillOpacity": 10,
            "lineWidth": 2,
            "showPoints": "never",
            "spanNulls": false,
            "stacking": { "group": "A", "mode": "none" }
          },
          "mappings": [],
          "unit": "short"
        },
        "overrides": []
      },
      "gridPos": { "h": 8, "w": 12, "x": 12, "y": 6 },
      "id": 5,
      "options": {
        "legend": { "calcs": [], "displayMode": "list", "placement": "bottom", "showLegend": true },
        "tooltip": { "mode": "multi", "sort": "desc" }
      },
      "pluginVersion": "12.0.0",
      "targets": [
        {
          "datasource": { "type": "prometheus", "uid": "${DS_PROMETHEUS}" },
          "expr": "sum(rate(resolute_webhook_decided_total[$__rate_interval])) * 3600",
          "legendFormat": "decided",
          "refId": "A"
        },
        {
          "datasource": { "type": "prometheus", "uid": "${DS_PROMETHEUS}" },
          "expr": "sum(rate(resolute_webhook_unauthorized_total[$__rate_interval])) * 3600",
          "legendFormat": "unauthorized",
          "refId": "B"
        },
        {
          "datasource": { "type": "prometheus", "uid": "${DS_PROMETHEUS}" },
          "expr": "sum(rate(resolute_webhook_skipped_total[$__rate_interval])) * 3600",
          "legendFormat": "skipped",
          "refId": "C"
        },
        {
          "datasource": { "type": "prometheus", "uid": "${DS_PROMETHEUS}" },
          "expr": "sum(rate(resolute_webhook_invalid_total[$__rate_interval])) * 3600",
          "legendFormat": "invalid",
          "refId": "D"
        }
      ],
      "title": "Webhook health (per hour)",
      "type": "timeseries"
    }
  ],
  "refresh": "1m",
  "schemaVersion": 41,
  "tags": ["resolute", "home-ops"],
  "templating": { "list": [] },
  "time": { "from": "now-7d", "to": "now" },
  "timepicker": {},
  "timezone": "browser",
  "title": "Resolute (shadow mode)",
  "uid": "resolute-shadow",
  "version": 1
}
